LICENSE
MANIFEST.in
README.rst
setup.py
django_ohm2_handlers_light.egg-info/PKG-INFO
django_ohm2_handlers_light.egg-info/SOURCES.txt
django_ohm2_handlers_light.egg-info/dependency_links.txt
django_ohm2_handlers_light.egg-info/requires.txt
django_ohm2_handlers_light.egg-info/top_level.txt
docs/INFO.txt
ohm2_handlers_light/__init__.py
ohm2_handlers_light/admin.py
ohm2_handlers_light/apps.py
ohm2_handlers_light/context_processors.py
ohm2_handlers_light/decorators.py
ohm2_handlers_light/definitions.py
ohm2_handlers_light/errors.py
ohm2_handlers_light/managers.py
ohm2_handlers_light/middlewares.py
ohm2_handlers_light/models.py
ohm2_handlers_light/parsers.py
ohm2_handlers_light/settings.py
ohm2_handlers_light/tests.py
ohm2_handlers_light/urls.py
ohm2_handlers_light/utils.py
ohm2_handlers_light/views.py
ohm2_handlers_light/email_handlers/__init__.py
ohm2_handlers_light/email_handlers/mailgun.py
ohm2_handlers_light/email_handlers/sendgrid.py
ohm2_handlers_light/email_handlers/__pycache__/__init__.cpython-35.pyc
ohm2_handlers_light/email_handlers/__pycache__/mailgun.cpython-35.pyc
ohm2_handlers_light/email_handlers/__pycache__/sendgrid.cpython-35.pyc
ohm2_handlers_light/management/.DS_Store
ohm2_handlers_light/management/__init__.py
ohm2_handlers_light/management/ohm2_get_base_error.py
ohm2_handlers_light/management/__pycache__/__init__.cpython-35.pyc
ohm2_handlers_light/management/commands/.DS_Store
ohm2_handlers_light/management/commands/__init__.py
ohm2_handlers_light/management/commands/get_base_error.py
ohm2_handlers_light/management/commands/ohm2_handlers_light_appapi.py
ohm2_handlers_light/management/commands/ohm2_handlers_light_base_error_code.py
ohm2_handlers_light/management/commands/ohm2_handlers_light_startapp.py
ohm2_handlers_light/management/commands/ohm2_handlers_test_command.py
ohm2_handlers_light/management/commands/__pycache__/__init__.cpython-35.pyc
ohm2_handlers_light/management/commands/__pycache__/get_base_error.cpython-35.pyc
ohm2_handlers_light/management/commands/__pycache__/handlers_create_api.cpython-35.pyc
ohm2_handlers_light/management/commands/__pycache__/handlers_startapp.cpython-35.pyc
ohm2_handlers_light/management/commands/__pycache__/handlers_test_command.cpython-35.pyc
